[
  {
    "id": 71,
    "nameKey": "sethek_card",
    "point": 47,
    "group": 5,
    "rate": 0.007633587786259542,
    "region": "",
    "groupCount": 131,
    "image": "sbta22585.webp"
  },
  {
    "id": 72,
    "nameKey": "underpass_ergate_card",
    "point": 49,
    "group": 5,
    "rate": 0.007633587786259542,
    "region": "",
    "groupCount": 131,
    "image": "sbta22586.webp"
  },
  {
    "id": 77,
    "nameKey": "aranya_card",
    "point": 50,
    "group": 5,
    "rate": 0.007633587786259542,
    "region": "",
    "groupCount": 131,
    "image": "sbta22591.webp"
  },
  {
    "id": 78,
    "nameKey": "kungji_card",
    "point": 50,
    "group": 5,
    "rate": 0.007633587786259542,
    "region": "",
    "groupCount": 131,
    "image": "sbta22592.webp"
  },
  {
    "id": 81,
    "nameKey": "guardian_kungji_card",
    "point": 49,
    "group": 5,
    "rate": 0.007633587786259542,
    "region": "",
    "groupCount": 131,
    "image": "sbta22595.webp"
  },
  {
    "id": 82,
    "nameKey": "elder_kungji_card",
    "point": 51,
    "group": 5,
    "rate": 0.007633587786259542,
    "region": "",
    "groupCount": 131,
    "image": "sbta22596.webp"
  },
  {
    "id": 155,
    "nameKey": "rukkha_card",
    "point": 49,
    "group": 5,
    "rate": 0.007633587786259542,
    "region": "",
    "groupCount": 131,
    "image": "sbta22669.webp"
  },
  {
    "id": 166,
    "nameKey": "talin_elfbane_card",
    "point": 53,
    "group": 5,
    "rate": 0.007633587786259542,
    "region": "",
    "groupCount": 131,
    "image": "sbta22680.webp"
  },
  {
    "id": 167,
    "nameKey": "sand_ergate_card",
    "point": 44,
    "group": 5,
    "rate": 0.007633587786259542,
    "region": "",
    "groupCount": 131,
    "image": "sbta30159.webp"
  },
  {
    "id": 170,
    "nameKey": "frillzard_card",
    "point": 44,
    "group": 5,
    "rate": 0.007633587786259542,
    "region": "",
    "groupCount": 131,
    "image": "sbta30162.webp"
  },
  {
    "id": 171,
    "nameKey": "giant_frillzard_card",
    "point": 46,
    "group": 5,
    "rate": 0.007633587786259542,
    "region": "",
    "groupCount": 131,
    "image": "sbta30163.webp"
  },
  {
    "id": 175,
    "nameKey": "fire_hammer_driller_card",
    "point": 46,
    "group": 5,
    "rate": 0.007633587786259542,
    "region": "",
    "groupCount": 131,
    "image": "sbta30167.webp"
  },
  {
    "id": 176,
    "nameKey": "power_shovel_card",
    "point": 45,
    "group": 5,
    "rate": 0.007633587786259542,
    "region": "",
    "groupCount": 131,
    "image": "sbta30168.webp"
  },
  {
    "id": 178,
    "nameKey": "sentry_keeper_no_2_card",
    "point": 53,
    "group": 5,
    "rate": 0.007633587786259542,
    "region": "",
    "groupCount": 131,
    "image": "sbta30170.webp"
  },
  {
    "id": 192,
    "nameKey": "mecha_taurus_card",
    "point": 46,
    "group": 5,
    "rate": 0.007633587786259542,
    "region": "",
    "groupCount": 131,
    "image": "sbta33168.webp"
  },
  {
    "id": 193,
    "nameKey": "void_card",
    "point": 51,
    "group": 5,
    "rate": 0.007633587786259542,
    "region": "",
    "groupCount": 131,
    "image": "sbta33169.webp"
  },
  {
    "id": 197,
    "nameKey": "garou_berserker",
    "point": 47,
    "group": 5,
    "rate": 0.007633587786259542,
    "region": "",
    "groupCount": 131,
    "image": "sbta53739.webp"
  },
  {
    "id": 198,
    "nameKey": "garou",
    "point": 44,
    "group": 5,
    "rate": 0.007633587786259542,
    "region": "",
    "groupCount": 131,
    "image": "sbta53740.webp"
  },
  {
    "id": 199,
    "nameKey": "garou_mage",
    "point": 50,
    "group": 5,
    "rate": 0.007633587786259542,
    "region": "",
    "groupCount": 131,
    "image": "sbta53741.webp"
  },
  {
    "id": 245,
    "nameKey": "dragon_knight",
    "point": 50,
    "group": 5,
    "rate": 0.007633587786259542,
    "region": "",
    "groupCount": 131,
    "image": "sbta80040.webp"
  },
  {
    "id": 246,
    "nameKey": "rama",
    "point": 50,
    "group": 5,
    "rate": 0.007633587786259542,
    "region": "",
    "groupCount": 131,
    "image": "sbta80041.webp"
  },
  {
    "id": 247,
    "nameKey": "geas",
    "point": 50,
    "group": 5,
    "rate": 0.007633587786259542,
    "region": "",
    "groupCount": 131,
    "image": "sbta80042.webp"
  },
  {
    "id": 248,
    "nameKey": "drakar",
    "point": 50,
    "group": 5,
    "rate": 0.007633587786259542,
    "region": "",
    "groupCount": 131,
    "image": "sbta80043.webp"
  },
  {
    "id": 249,
    "nameKey": "spell_knight",
    "point": 50,
    "group": 5,
    "rate": 0.007633587786259542,
    "region": "",
    "groupCount": 131,
    "image": "sbta80044.webp"
  },
  {
    "id": 250,
    "nameKey": "executioner",
    "point": 50,
    "group": 5,
    "rate": 0.007633587786259542,
    "region": "",
    "groupCount": 131,
    "image": "sbta80045.webp"
  },
  {
    "id": 251,
    "nameKey": "crossbowman",
    "point": 50,
    "group": 5,
    "rate": 0.007633587786259542,
    "region": "",
    "groupCount": 131,
    "image": "sbta80046.webp"
  },
  {
    "id": 252,
    "nameKey": "dancer",
    "point": 50,
    "group": 5,
    "rate": 0.007633587786259542,
    "region": "",
    "groupCount": 131,
    "image": "sbta80049.webp"
  },
  {
    "id": 253,
    "nameKey": "assassin",
    "point": 50,
    "group": 5,
    "rate": 0.007633587786259542,
    "region": "",
    "groupCount": 131,
    "image": "sbta80050.webp"
  },
  {
    "id": 254,
    "nameKey": "sword_master",
    "point": 50,
    "group": 5,
    "rate": 0.007633587786259542,
    "region": "",
    "groupCount": 131,
    "image": "sbta80051.webp"
  },
  {
    "id": 255,
    "nameKey": "arbiter",
    "point": 50,
    "group": 5,
    "rate": 0.007633587786259542,
    "region": "",
    "groupCount": 131,
    "image": "sbta80052.webp"
  },
  {
    "id": 256,
    "nameKey": "gunslinger",
    "point": 50,
    "group": 5,
    "rate": 0.007633587786259542,
    "region": "",
    "groupCount": 131,
    "image": "sbta80053.webp"
  },
  {
    "id": 257,
    "nameKey": "druid",
    "point": 50,
    "group": 5,
    "rate": 0.007633587786259542,
    "region": "",
    "groupCount": 131,
    "image": "sbta80055.webp"
  },
  {
    "id": 258,
    "nameKey": "harpe",
    "point": 50,
    "group": 5,
    "rate": 0.007633587786259542,
    "region": "",
    "groupCount": 131,
    "image": "sbta80056.webp"
  },
  {
    "id": 259,
    "nameKey": "duell_edna",
    "point": 50,
    "group": 5,
    "rate": 0.007633587786259542,
    "region": "",
    "groupCount": 131,
    "image": "sbta80058.webp"
  },
  {
    "id": 260,
    "nameKey": "edna",
    "point": 50,
    "group": 5,
    "rate": 0.007633587786259542,
    "region": "",
    "groupCount": 131,
    "image": "sbta80059.webp"
  },
  {
    "id": 261,
    "nameKey": "duell_edna",
    "point": 50,
    "group": 5,
    "rate": 0.007633587786259542,
    "region": "",
    "groupCount": 131,
    "image": "sbta80061.webp"
  },
  {
    "id": 262,
    "nameKey": "jeeves_alfred",
    "point": 50,
    "group": 5,
    "rate": 0.007633587786259542,
    "region": "",
    "groupCount": 131,
    "image": "sbta80062.webp"
  },
  {
    "id": 343,
    "nameKey": "mournful_passenger",
    "point": 55,
    "group": 5,
    "rate": 0.007633587786259542,
    "region": "",
    "groupCount": 131,
    "image": "sbta80772.webp"
  },
  {
    "id": 344,
    "nameKey": "monster_train_attendant",
    "point": 55,
    "group": 5,
    "rate": 0.007633587786259542,
    "region": "",
    "groupCount": 131,
    "image": "sbta80773.webp"
  },
  {
    "id": 345,
    "nameKey": "monster_train_security_personnel",
    "point": 55,
    "group": 5,
    "rate": 0.007633587786259542,
    "region": "",
    "groupCount": 131,
    "image": "sbta80774.webp"
  },
  {
    "id": 346,
    "nameKey": "escaped_prisoner",
    "point": 45,
    "group": 5,
    "rate": 0.007633587786259542,
    "region": "",
    "groupCount": 131,
    "image": "sbta80775.webp"
  },
  {
    "id": 347,
    "nameKey": "casey_bones",
    "point": 48,
    "group": 5,
    "rate": 0.007633587786259542,
    "region": "",
    "groupCount": 131,
    "image": "sbta80776.webp"
  },
  {
    "id": 348,
    "nameKey": "epic_death_furnace_301",
    "point": 54,
    "group": 5,
    "rate": 0.007633587786259542,
    "region": "",
    "groupCount": 131,
    "image": "sbta80777.webp"
  },
  {
    "id": 349,
    "nameKey": "relic_death_furnace_301",
    "point": 54,
    "group": 5,
    "rate": 0.007633587786259542,
    "region": "",
    "groupCount": 131,
    "image": "sbta80778.webp"
  },
  {
    "id": 356,
    "nameKey": "dark_elven_scout",
    "point": 47,
    "group": 5,
    "rate": 0.007633587786259542,
    "region": "",
    "groupCount": 131,
    "image": "sbta97755.webp"
  },
  {
    "id": 357,
    "nameKey": "dark_elven_assassin",
    "point": 47,
    "group": 5,
    "rate": 0.007633587786259542,
    "region": "",
    "groupCount": 131,
    "image": "sbta97756.webp"
  },
  {
    "id": 358,
    "nameKey": "dark_elven_magic_archer",
    "point": 53,
    "group": 5,
    "rate": 0.007633587786259542,
    "region": "",
    "groupCount": 131,
    "image": "sbta97757.webp"
  },
  {
    "id": 359,
    "nameKey": "dark_elven_horseman",
    "point": 52,
    "group": 5,
    "rate": 0.007633587786259542,
    "region": "",
    "groupCount": 131,
    "image": "sbta97758.webp"
  },
  {
    "id": 361,
    "nameKey": "guardian_spirit",
    "point": 44,
    "group": 5,
    "rate": 0.007633587786259542,
    "region": "",
    "groupCount": 131,
    "image": "sbta97760.webp"
  },
  {
    "id": 362,
    "nameKey": "royal_elven_guard",
    "point": 47,
    "group": 5,
    "rate": 0.007633587786259542,
    "region": "",
    "groupCount": 131,
    "image": "sbta97761.webp"
  },
  {
    "id": 363,
    "nameKey": "elite_elven_mage",
    "point": 50,
    "group": 5,
    "rate": 0.007633587786259542,
    "region": "",
    "groupCount": 131,
    "image": "sbta97762.webp"
  },
  {
    "id": 364,
    "nameKey": "golem",
    "point": 53,
    "group": 5,
    "rate": 0.007633587786259542,
    "region": "",
    "groupCount": 131,
    "image": "sbta97763.webp"
  },
  {
    "id": 372,
    "nameKey": "tiger_trader",
    "point": 46,
    "group": 5,
    "rate": 0.007633587786259542,
    "region": "",
    "groupCount": 131,
    "image": "sbta101712.webp"
  },
  {
    "id": 376,
    "nameKey": "gumiho",
    "point": 48,
    "group": 5,
    "rate": 0.007633587786259542,
    "region": "",
    "groupCount": 131,
    "image": "sbta101716.webp"
  },
  {
    "id": 385,
    "nameKey": "hooded_scorpion",
    "point": 48,
    "group": 5,
    "rate": 0.007633587786259542,
    "region": "",
    "groupCount": 131,
    "image": "sbta107575.webp"
  },
  {
    "id": 387,
    "nameKey": "vanisher",
    "point": 50,
    "group": 5,
    "rate": 0.007633587786259542,
    "region": "",
    "groupCount": 131,
    "image": "sbta107749.webp"
  },
  {
    "id": 388,
    "nameKey": "dusk_bringer",
    "point": 50,
    "group": 5,
    "rate": 0.007633587786259542,
    "region": "",
    "groupCount": 131,
    "image": "sbta107750.webp"
  },
  {
    "id": 389,
    "nameKey": "awakened_card",
    "point": 50,
    "group": 5,
    "rate": 0.007633587786259542,
    "region": "",
    "groupCount": 131,
    "image": "sbta107751.webp"
  },
  {
    "id": 390,
    "nameKey": "chaotic",
    "point": 50,
    "group": 5,
    "rate": 0.007633587786259542,
    "region": "",
    "groupCount": 131,
    "image": "sbta107752.webp"
  },
  {
    "id": 391,
    "nameKey": "chosen",
    "point": 50,
    "group": 5,
    "rate": 0.007633587786259542,
    "region": "",
    "groupCount": 131,
    "image": "sbta107753.webp"
  },
  {
    "id": 395,
    "nameKey": "anubis",
    "point": 50,
    "group": 5,
    "rate": 0.007633587786259542,
    "region": "",
    "groupCount": 131,
    "image": "sbta109082.webp"
  },
  {
    "id": 397,
    "nameKey": "commander_the_dark_sword",
    "point": 54,
    "group": 5,
    "rate": 0.007633587786259542,
    "region": "",
    "groupCount": 131,
    "image": "sbta110761.webp"
  },
  {
    "id": 398,
    "nameKey": "commander_the_dark_staff",
    "point": 54,
    "group": 5,
    "rate": 0.007633587786259542,
    "region": "",
    "groupCount": 131,
    "image": "sbta110762.webp"
  },
  {
    "id": 400,
    "nameKey": "graham_s_illusion",
    "point": 54,
    "group": 5,
    "rate": 0.007633587786259542,
    "region": "",
    "groupCount": 131,
    "image": "sbta110764.webp"
  },
  {
    "id": 477,
    "nameKey": "harrier_carnivorous_plant",
    "point": 45,
    "group": 5,
    "rate": 0.007633587786259542,
    "region": "",
    "groupCount": 131,
    "image": "sbta163668.webp"
  },
  {
    "id": 479,
    "nameKey": "harrier_dwarf_rifleman",
    "point": 44,
    "group": 5,
    "rate": 0.007633587786259542,
    "region": "",
    "groupCount": 131,
    "image": "sbta163672.webp"
  },
  {
    "id": 480,
    "nameKey": "harrier_native_leader",
    "point": 48,
    "group": 5,
    "rate": 0.007633587786259542,
    "region": "",
    "groupCount": 131,
    "image": "sbta163674.webp"
  },
  {
    "id": 482,
    "nameKey": "harrier_guardian_spirit",
    "point": 49,
    "group": 5,
    "rate": 0.007633587786259542,
    "region": "",
    "groupCount": 131,
    "image": "sbta163676.webp"
  },
  {
    "id": 483,
    "nameKey": "harrier_vile_naga",
    "point": 50,
    "group": 5,
    "rate": 0.007633587786259542,
    "region": "",
    "groupCount": 131,
    "image": "sbta163678.webp"
  },
  {
    "id": 486,
    "nameKey": "harrier_orc_warrior",
    "point": 45,
    "group": 5,
    "rate": 0.007633587786259542,
    "region": "",
    "groupCount": 131,
    "image": "sbta163681.webp"
  },
  {
    "id": 487,
    "nameKey": "harrier_garou_berserker",
    "point": 49,
    "group": 5,
    "rate": 0.007633587786259542,
    "region": "",
    "groupCount": 131,
    "image": "sbta163682.webp"
  },
  {
    "id": 488,
    "nameKey": "harrier_hooded_hound",
    "point": 46,
    "group": 5,
    "rate": 0.007633587786259542,
    "region": "",
    "groupCount": 131,
    "image": "sbta163683.webp"
  },
  {
    "id": 490,
    "nameKey": "harrier_left_basilisk",
    "point": 55,
    "group": 5,
    "rate": 0.007633587786259542,
    "region": "",
    "groupCount": 131,
    "image": "sbta163686.webp"
  },
  {
    "id": 492,
    "nameKey": "harrier_dwarf_engineer",
    "point": 47,
    "group": 5,
    "rate": 0.007633587786259542,
    "region": "",
    "groupCount": 131,
    "image": "sbta163688.webp"
  },
  {
    "id": 494,
    "nameKey": "harrier_royal_elven_guard",
    "point": 48,
    "group": 5,
    "rate": 0.007633587786259542,
    "region": "",
    "groupCount": 131,
    "image": "sbta163690.webp"
  },
  {
    "id": 495,
    "nameKey": "harrier_paraminimy",
    "point": 49,
    "group": 5,
    "rate": 0.007633587786259542,
    "region": "",
    "groupCount": 131,
    "image": "sbta163691.webp"
  },
  {
    "id": 498,
    "nameKey": "harrier_miston",
    "point": 50,
    "group": 5,
    "rate": 0.007633587786259542,
    "region": "",
    "groupCount": 131,
    "image": "sbta163694.webp"
  },
  {
    "id": 500,
    "nameKey": "harrier_sataniel_s_warrior",
    "point": 54,
    "group": 5,
    "rate": 0.007633587786259542,
    "region": "",
    "groupCount": 131,
    "image": "sbta163696.webp"
  },
  {
    "id": 502,
    "nameKey": "harrier_troll",
    "point": 51,
    "group": 5,
    "rate": 0.007633587786259542,
    "region": "",
    "groupCount": 131,
    "image": "sbta163699.webp"
  },
  {
    "id": 503,
    "nameKey": "harrier_frillzard",
    "point": 45,
    "group": 5,
    "rate": 0.007633587786259542,
    "region": "",
    "groupCount": 131,
    "image": "sbta163700.webp"
  },
  {
    "id": 507,
    "nameKey": "harrier_fytros",
    "point": 53,
    "group": 5,
    "rate": 0.007633587786259542,
    "region": "",
    "groupCount": 131,
    "image": "sbta163706.webp"
  },
  {
    "id": 509,
    "nameKey": "harrier_iron_guard",
    "point": 51,
    "group": 5,
    "rate": 0.007633587786259542,
    "region": "",
    "groupCount": 131,
    "image": "sbta163709.webp"
  },
  {
    "id": 512,
    "nameKey": "harrier_dark_elven_magic_archer",
    "point": 49,
    "group": 5,
    "rate": 0.007633587786259542,
    "region": "",
    "groupCount": 131,
    "image": "sbta163713.webp"
  },
  {
    "id": 513,
    "nameKey": "harrier_dark_elven_horseman",
    "point": 49,
    "group": 5,
    "rate": 0.007633587786259542,
    "region": "",
    "groupCount": 131,
    "image": "sbta163714.webp"
  },
  {
    "id": 514,
    "nameKey": "harrier_violent_drillmon",
    "point": 50,
    "group": 5,
    "rate": 0.007633587786259542,
    "region": "",
    "groupCount": 131,
    "image": "sbta163715.webp"
  },
  {
    "id": 515,
    "nameKey": "harrier_gargoyle",
    "point": 48,
    "group": 5,
    "rate": 0.007633587786259542,
    "region": "",
    "groupCount": 131,
    "image": "sbta163716.webp"
  },
  {
    "id": 518,
    "nameKey": "harrier_decoy",
    "point": 45,
    "group": 5,
    "rate": 0.007633587786259542,
    "region": "",
    "groupCount": 131,
    "image": "sbta163719.webp"
  },
  {
    "id": 519,
    "nameKey": "harrier_goblin",
    "point": 45,
    "group": 5,
    "rate": 0.007633587786259542,
    "region": "",
    "groupCount": 131,
    "image": "sbta163720.webp"
  },
  {
    "id": 521,
    "nameKey": "harrier_garou_mage",
    "point": 49,
    "group": 5,
    "rate": 0.007633587786259542,
    "region": "",
    "groupCount": 131,
    "image": "sbta163722.webp"
  },
  {
    "id": 522,
    "nameKey": "harrier_hooded_jackal",
    "point": 46,
    "group": 5,
    "rate": 0.007633587786259542,
    "region": "",
    "groupCount": 131,
    "image": "sbta163723.webp"
  },
  {
    "id": 523,
    "nameKey": "harrier_scorpis",
    "point": 55,
    "group": 5,
    "rate": 0.007633587786259542,
    "region": "",
    "groupCount": 131,
    "image": "sbta163724.webp"
  },
  {
    "id": 524,
    "nameKey": "harrier_scorping",
    "point": 46,
    "group": 5,
    "rate": 0.007633587786259542,
    "region": "",
    "groupCount": 131,
    "image": "sbta163725.webp"
  },
  {
    "id": 525,
    "nameKey": "harrier_lich",
    "point": 46,
    "group": 5,
    "rate": 0.007633587786259542,
    "region": "",
    "groupCount": 131,
    "image": "sbta163726.webp"
  },
  {
    "id": 527,
    "nameKey": "harrier_dwarl_overseer",
    "point": 47,
    "group": 5,
    "rate": 0.007633587786259542,
    "region": "",
    "groupCount": 131,
    "image": "sbta163728.webp"
  },
  {
    "id": 530,
    "nameKey": "harrier_elite_elven_mage",
    "point": 54,
    "group": 5,
    "rate": 0.007633587786259542,
    "region": "",
    "groupCount": 131,
    "image": "sbta163732.webp"
  },
  {
    "id": 531,
    "nameKey": "harrier_tech_guard",
    "point": 52,
    "group": 5,
    "rate": 0.007633587786259542,
    "region": "",
    "groupCount": 131,
    "image": "sbta163733.webp"
  },
  {
    "id": 532,
    "nameKey": "harrier_assassin_champion",
    "point": 46,
    "group": 5,
    "rate": 0.007633587786259542,
    "region": "",
    "groupCount": 131,
    "image": "sbta163734.webp"
  },
  {
    "id": 533,
    "nameKey": "harrier_beholder",
    "point": 49,
    "group": 5,
    "rate": 0.007633587786259542,
    "region": "",
    "groupCount": 131,
    "image": "sbta163735.webp"
  },
  {
    "id": 535,
    "nameKey": "harrier_assassin_master",
    "point": 50,
    "group": 5,
    "rate": 0.007633587786259542,
    "region": "",
    "groupCount": 131,
    "image": "sbta163737.webp"
  },
  {
    "id": 540,
    "nameKey": "harrier_harpy_queen",
    "point": 49,
    "group": 5,
    "rate": 0.007633587786259542,
    "region": "",
    "groupCount": 131,
    "image": "sbta163754.webp"
  },
  {
    "id": 542,
    "nameKey": "harrier_poison_cactus",
    "point": 50,
    "group": 5,
    "rate": 0.007633587786259542,
    "region": "",
    "groupCount": 131,
    "image": "sbta163756.webp"
  },
  {
    "id": 543,
    "nameKey": "harrier_snowfield_shield_bearer",
    "point": 54,
    "group": 5,
    "rate": 0.007633587786259542,
    "region": "",
    "groupCount": 131,
    "image": "sbta163757.webp"
  },
  {
    "id": 544,
    "nameKey": "harrier_sand_spirit",
    "point": 55,
    "group": 5,
    "rate": 0.007633587786259542,
    "region": "",
    "groupCount": 131,
    "image": "sbta163758.webp"
  },
  {
    "id": 545,
    "nameKey": "harrier_magma_paradom",
    "point": 53,
    "group": 5,
    "rate": 0.007633587786259542,
    "region": "",
    "groupCount": 131,
    "image": "sbta163759.webp"
  },
  {
    "id": 546,
    "nameKey": "harrier_onyx_wendy",
    "point": 55,
    "group": 5,
    "rate": 0.007633587786259542,
    "region": "",
    "groupCount": 131,
    "image": "sbta163760.webp"
  },
  {
    "id": 547,
    "nameKey": "harrier_wyrm_spawn",
    "point": 53,
    "group": 5,
    "rate": 0.007633587786259542,
    "region": "",
    "groupCount": 131,
    "image": "sbta163761.webp"
  },
  {
    "id": 548,
    "nameKey": "harrier_snowfield_spearman",
    "point": 48,
    "group": 5,
    "rate": 0.007633587786259542,
    "region": "",
    "groupCount": 131,
    "image": "sbta163762.webp"
  },
  {
    "id": 549,
    "nameKey": "harrier_rock_slime",
    "point": 52,
    "group": 5,
    "rate": 0.007633587786259542,
    "region": "",
    "groupCount": 131,
    "image": "sbta163763.webp"
  },
  {
    "id": 550,
    "nameKey": "harrier_snowfield_tempest",
    "point": 51,
    "group": 5,
    "rate": 0.007633587786259542,
    "region": "",
    "groupCount": 131,
    "image": "sbta163764.webp"
  },
  {
    "id": 551,
    "nameKey": "harrier_dwarf_warrior",
    "point": 50,
    "group": 5,
    "rate": 0.007633587786259542,
    "region": "",
    "groupCount": 131,
    "image": "sbta163806.webp"
  },
  {
    "id": 552,
    "nameKey": "harrier_cyclops_sentry",
    "point": 45,
    "group": 5,
    "rate": 0.007633587786259542,
    "region": "",
    "groupCount": 131,
    "image": "sbta163819.webp"
  },
  {
    "id": 553,
    "nameKey": "harrier_elvin_assassin",
    "point": 48,
    "group": 5,
    "rate": 0.007633587786259542,
    "region": "",
    "groupCount": 131,
    "image": "sbta163820.webp"
  },
  {
    "id": 554,
    "nameKey": "harrier_obsidian_demon",
    "point": 50,
    "group": 5,
    "rate": 0.007633587786259542,
    "region": "",
    "groupCount": 131,
    "image": "sbta164117.webp"
  },
  {
    "id": 555,
    "nameKey": "harrier_highlander_s_illusion",
    "point": 49,
    "group": 5,
    "rate": 0.007633587786259542,
    "region": "",
    "groupCount": 131,
    "image": "sbta164118.webp"
  },
  {
    "id": 556,
    "nameKey": "harrier_sand_dinergate",
    "point": 49,
    "group": 5,
    "rate": 0.007633587786259542,
    "region": "",
    "groupCount": 131,
    "image": "sbta164119.webp"
  },
  {
    "id": 557,
    "nameKey": "harrier_native_spearman",
    "point": 49,
    "group": 5,
    "rate": 0.007633587786259542,
    "region": "",
    "groupCount": 131,
    "image": "sbta164120.webp"
  },
  {
    "id": 559,
    "nameKey": "iron_infantry",
    "point": 50,
    "group": 5,
    "rate": 0.007633587786259542,
    "region": "",
    "groupCount": 131,
    "image": "sbta165150.webp"
  },
  {
    "id": 561,
    "nameKey": "iron_archer",
    "point": 50,
    "group": 5,
    "rate": 0.007633587786259542,
    "region": "",
    "groupCount": 131,
    "image": "sbta165152.webp"
  },
  {
    "id": 564,
    "nameKey": "goblin_worker",
    "point": 50,
    "group": 5,
    "rate": 0.007633587786259542,
    "region": "",
    "groupCount": 131,
    "image": "sbta165155.webp"
  },
  {
    "id": 566,
    "nameKey": "goblin_jester",
    "point": 53,
    "group": 5,
    "rate": 0.007633587786259542,
    "region": "",
    "groupCount": 131,
    "image": "sbta165157.webp"
  },
  {
    "id": 569,
    "nameKey": "demon_bat",
    "point": 44,
    "group": 5,
    "rate": 0.007633587786259542,
    "region": "",
    "groupCount": 131,
    "image": "sbta165160.webp"
  },
  {
    "id": 570,
    "nameKey": "raging_demon_bat",
    "point": 44,
    "group": 5,
    "rate": 0.007633587786259542,
    "region": "",
    "groupCount": 131,
    "image": "sbta165161.webp"
  },
  {
    "id": 576,
    "nameKey": "templo_apostle",
    "point": 46,
    "group": 5,
    "rate": 0.007633587786259542,
    "region": "",
    "groupCount": 131,
    "image": "sbta167995.webp"
  },
  {
    "id": 577,
    "nameKey": "pure_white_apostle",
    "point": 55,
    "group": 5,
    "rate": 0.007633587786259542,
    "region": "",
    "groupCount": 131,
    "image": "sbta167996.webp"
  },
  {
    "id": 579,
    "nameKey": "sentry_robot",
    "point": 52,
    "group": 5,
    "rate": 0.007633587786259542,
    "region": "",
    "groupCount": 131,
    "image": "sbta167998.webp"
  },
  {
    "id": 580,
    "nameKey": "elite_sentry_robot",
    "point": 55,
    "group": 5,
    "rate": 0.007633587786259542,
    "region": "",
    "groupCount": 131,
    "image": "sbta167999.webp"
  },
  {
    "id": 582,
    "nameKey": "golem_of_reversing_time",
    "point": 55,
    "group": 5,
    "rate": 0.007633587786259542,
    "region": "",
    "groupCount": 131,
    "image": "sbta168001.webp"
  },
  {
    "id": 583,
    "nameKey": "golem_of_suspending_time",
    "point": 55,
    "group": 5,
    "rate": 0.007633587786259542,
    "region": "",
    "groupCount": 131,
    "image": "sbta168002.webp"
  },
  {
    "id": 620,
    "nameKey": "the_crucible",
    "point": 50,
    "group": 5,
    "rate": 0.007633587786259542,
    "region": "",
    "groupCount": 131,
    "image": "sbta178685.webp"
  },
  {
    "id": 621,
    "nameKey": "sanctum_of_destruction",
    "point": 50,
    "group": 5,
    "rate": 0.007633587786259542,
    "region": "",
    "groupCount": 131,
    "image": "sbta178686.webp"
  },
  {
    "id": 622,
    "nameKey": "wizard_s_labyrinth",
    "point": 50,
    "group": 5,
    "rate": 0.007633587786259542,
    "region": "",
    "groupCount": 131,
    "image": "sbta178687.webp"
  }
]